Metadata-Version: 2.1
Name: EpiClass
Version: 2.2.4
Summary: Optimizing and predicting performance of DNA methylation biomarkers using sequence methylation density information.
Home-page: https://github.com/bmill3r/EpiClass
Author: Brendan F. Miller
Author-email: bmille79@jh.edu
License: Public Domain
Download-URL: https://github.com/bmill3r/EpiClass/dist/EpiClass-2.2.4.tar.gz
Platform: UNKNOWN
Classifier: Programming Language :: Python :: 3 :: Only
Classifier: Operating System :: OS Independent
Classifier: Development Status :: 4 - Beta
Classifier: License :: Public Domain
Classifier: Intended Audience :: Science/Research
Classifier: Topic :: Scientific/Engineering :: Bio-Informatics
Classifier: Topic :: Scientific/Engineering :: Medical Science Apps.
Classifier: Environment :: Console
